bullfinch/__init__.py
bullfinch/core.py
bullfinch/decorators.py
bullfinch-0.2.0.dist-info/METADATA
bullfinch-0.2.0.dist-info/WHEEL
bullfinch-0.2.0.dist-info/top_level.txt
bullfinch-0.2.0.dist-info/RECORD
