Metadata-Version: 2.4
Name: bullfinch
Version: 0.2.0
Summary: A lightweight web framework like StillSite
Author: Vadim
Author-email: somerare22@gmail.com
Classifier: Programming Language :: Python :: 3
Classifier: Framework :: Flask
Classifier: License :: OSI Approved :: MIT License
Dynamic: author
Dynamic: author-email
Dynamic: classifier
Dynamic: description
Dynamic: description-content-type
Dynamic: summary
